setup.py
src/py_soocial.egg-info/PKG-INFO
src/py_soocial.egg-info/SOURCES.txt
src/py_soocial.egg-info/dependency_links.txt
src/py_soocial.egg-info/requires.txt
src/py_soocial.egg-info/top_level.txt
src/py_soocial.egg-info/zip-safe
src/soocial/README.rst
src/soocial/__init__.py
src/soocial/client.py
src/soocial/xml2dict.py