Metadata-Version: 1.0
Name: py-soocial
Version: 0.2.1
Summary: Python bindings for the http://www.soocial.com developer API
Home-page: http://github.com/thruflo/py-soocial/tree/master
Author: thruflo
Author-email: thruflo@googlemail.com
License: Public Domain
Platform: UNKNOWN
Classifier: Development Status :: 3 - Alpha
Classifier: Environment :: Web Environment
Classifier: Intended Audience :: Developers
Classifier: License :: Public Domain
Classifier: Programming Language :: Python
